odo/__init__.py
odo/_version.py
odo/append.py
odo/chunks.py
odo/compatibility.py
odo/convert.py
odo/core.py
odo/create.py
odo/directory.py
odo/dot.py
odo/drop.py
odo/into.py
odo/numpy_dtype.py
odo/odo.py
odo/regex.py
odo/resource.py
odo/temp.py
odo/utils.py
odo/backends/__init__.py
odo/backends/aws.py
odo/backends/bcolz.py
odo/backends/bokeh.py
odo/backends/csv.py
odo/backends/dask.py
odo/backends/h5py.py
odo/backends/hdfs.py
odo/backends/hdfstore.py
odo/backends/json.py
odo/backends/mongo.py
odo/backends/pandas.py
odo/backends/pytables.py
odo/backends/sas.py
odo/backends/spark.py
odo/backends/sparksql.py
odo/backends/sql.py
odo/backends/sql_csv.py
odo/backends/ssh.py
odo/backends/text.py
odo/backends/url.py
odo/backends/tests/__init__.py
odo/backends/tests/airline.sas7bdat
odo/backends/tests/conftest.py
odo/backends/tests/dummydata.csv
odo/backends/tests/encoding.csv
odo/backends/tests/test_bcolz.py
odo/backends/tests/test_bokeh.py
odo/backends/tests/test_csv.py
odo/backends/tests/test_dask_array.py
odo/backends/tests/test_dask_bag.py
odo/backends/tests/test_dask_dataframe.py
odo/backends/tests/test_h5py.py
odo/backends/tests/test_hdfs.py
odo/backends/tests/test_hdfstore.py
odo/backends/tests/test_json.py
odo/backends/tests/test_mongo.py
odo/backends/tests/test_mysql.py
odo/backends/tests/test_pandas.py
odo/backends/tests/test_postgres.py
odo/backends/tests/test_pytables.py
odo/backends/tests/test_s3.py
odo/backends/tests/test_s3_redshift.py
odo/backends/tests/test_sas.py
odo/backends/tests/test_spark.py
odo/backends/tests/test_sparksql.py
odo/backends/tests/test_sql.py
odo/backends/tests/test_sqlite.py
odo/backends/tests/test_ssh.py
odo/backends/tests/test_text.py
odo/backends/tests/test_url.py
odo/tests/__init__.py
odo/tests/test_append.py
odo/tests/test_chunks.py
odo/tests/test_convert.py
odo/tests/test_core.py
odo/tests/test_directory.py
odo/tests/test_into.py
odo_fixpandas20-0.5.3.dist-info/METADATA
odo_fixpandas20-0.5.3.dist-info/RECORD
odo_fixpandas20-0.5.3.dist-info/WHEEL
odo_fixpandas20-0.5.3.dist-info/top_level.txt
