Metadata-Version: 2.1
Name: odo-fixpandas20
Version: 0.5.3
Summary: Data migration utilities
Home-page: https://github.com/blaze/odo
Author: Blaze development team
Author-email: blaze-dev@continuum.io
License: BSD
Keywords: odo data conversion hdf5 sql blaze
Platform: UNKNOWN
Provides-Extra: all
Provides-Extra: h5py
Provides-Extra: postgres
Provides-Extra: mongo
Provides-Extra: ssh
Provides-Extra: pytables
Provides-Extra: aws
Provides-Extra: bcolz
Provides-Extra: ci
Provides-Extra: mysql
Provides-Extra: sas
Provides-Extra: test
Provides-Extra: bokeh
Provides-Extra: sql
Requires-Dist: datashape (>=0.5.0)
Requires-Dist: numpy (>=1.7)
Requires-Dist: pandas (>=0.20.3)
Requires-Dist: toolz (>=0.7.3)
Requires-Dist: multipledispatch (>=0.4.7)
Requires-Dist: networkx (<2.0,>=1.0)
Requires-Dist: dask (>=0.11.1)
Provides-Extra: all
Requires-Dist: h5py (>=2.6.0); extra == 'all'
Requires-Dist: pymongo (<3.0.0,>2.9.0); extra == 'all'
Requires-Dist: paramiko (>=2.0.0); extra == 'all'
Requires-Dist: tables (>=3.3.0); extra == 'all'
Requires-Dist: boto (>=2.43.0); extra == 'all'
Requires-Dist: bcolz (<1.0.0,>=0.12.0); extra == 'all'
Requires-Dist: pymysql (>=0.7); extra == 'all'
Requires-Dist: sqlalchemy (>=0.8.0); extra == 'all'
Requires-Dist: sas7bdat (>=2.0.0); extra == 'all'
Requires-Dist: bokeh (>=0.12); extra == 'all'
Requires-Dist: psycopg2 (>=2.6.0); extra == 'all'
Requires-Dist: sqlalchemy (>=0.8.0); extra == 'all'
Requires-Dist: sqlalchemy (>=0.8.0); extra == 'all'
Provides-Extra: aws
Requires-Dist: boto (>=2.43.0); extra == 'aws'
Provides-Extra: bcolz
Requires-Dist: bcolz (<1.0.0,>=0.12.0); extra == 'bcolz'
Provides-Extra: bokeh
Requires-Dist: bokeh (>=0.12); extra == 'bokeh'
Provides-Extra: ci
Requires-Dist: bcolz (==0.12.1); extra == 'ci'
Requires-Dist: bokeh (==0.12.3); extra == 'ci'
Requires-Dist: boto3 (==1.4.1); extra == 'ci'
Requires-Dist: botocore (==1.4.68); extra == 'ci'
Requires-Dist: cffi (==1.8.3); extra == 'ci'
Requires-Dist: click (==6.6); extra == 'ci'
Requires-Dist: cloudpickle (==0.2.1); extra == 'ci'
Requires-Dist: cryptography (==1.5.2); extra == 'ci'
Requires-Dist: dask (==0.11.1); extra == 'ci'
Requires-Dist: decorator (==4.0.10); extra == 'ci'
Requires-Dist: distributed (==1.13.3); extra == 'ci'
Requires-Dist: docutils (==0.12); extra == 'ci'
Requires-Dist: h5py (==2.6.0); extra == 'ci'
Requires-Dist: HeapDict (==1.0.0); extra == 'ci'
Requires-Dist: idna (==2.1); extra == 'ci'
Requires-Dist: Jinja2 (==2.8); extra == 'ci'
Requires-Dist: jmespath (==0.9.0); extra == 'ci'
Requires-Dist: locket (==0.2.0); extra == 'ci'
Requires-Dist: MarkupSafe (==0.23); extra == 'ci'
Requires-Dist: mock (==2.0.0); extra == 'ci'
Requires-Dist: msgpack-python (==0.4.8); extra == 'ci'
Requires-Dist: multipledispatch (==0.4.9); extra == 'ci'
Requires-Dist: networkx (==1.11); extra == 'ci'
Requires-Dist: numexpr (==2.6.1); extra == 'ci'
Requires-Dist: numpy (==1.11.2); extra == 'ci'
Requires-Dist: pandas (==0.19.0); extra == 'ci'
Requires-Dist: paramiko (==2.0.2); extra == 'ci'
Requires-Dist: partd (==0.3.6); extra == 'ci'
Requires-Dist: psutil (==4.4.2); extra == 'ci'
Requires-Dist: psycopg2 (==2.6.2); extra == 'ci'
Requires-Dist: py (==1.4.34); extra == 'ci'
Requires-Dist: pyasn1 (==0.1.9); extra == 'ci'
Requires-Dist: pycparser (==2.17); extra == 'ci'
Requires-Dist: pymongo (==2.9.4); extra == 'ci'
Requires-Dist: PyMySQL (==0.7.9); extra == 'ci'
Requires-Dist: pytest (==3.2.3); extra == 'ci'
Requires-Dist: python-dateutil (==2.5.3); extra == 'ci'
Requires-Dist: pytz (==2016.7); extra == 'ci'
Requires-Dist: pywebhdfs (==0.4.1); extra == 'ci'
Requires-Dist: PyYAML (==3.12); extra == 'ci'
Requires-Dist: requests (==2.11.1); extra == 'ci'
Requires-Dist: s3fs (==0.0.7); extra == 'ci'
Requires-Dist: s3transfer (==0.1.9); extra == 'ci'
Requires-Dist: sas7bdat (==2.0.7); extra == 'ci'
Requires-Dist: six (==1.10.0); extra == 'ci'
Requires-Dist: SQLAlchemy (==1.1.3); extra == 'ci'
Requires-Dist: tables (==3.3.0); extra == 'ci'
Requires-Dist: tblib (==1.3.0); extra == 'ci'
Requires-Dist: toolz (==0.8.0); extra == 'ci'
Requires-Dist: tornado (==4.4.2); extra == 'ci'
Requires-Dist: zict (==0.0.3); extra == 'ci'
Provides-Extra: h5py
Requires-Dist: h5py (>=2.6.0); extra == 'h5py'
Provides-Extra: mongo
Requires-Dist: pymongo (<3.0.0,>2.9.0); extra == 'mongo'
Provides-Extra: mysql
Requires-Dist: pymysql (>=0.7); extra == 'mysql'
Requires-Dist: sqlalchemy (>=0.8.0); extra == 'mysql'
Provides-Extra: postgres
Requires-Dist: psycopg2 (>=2.6.0); extra == 'postgres'
Requires-Dist: sqlalchemy (>=0.8.0); extra == 'postgres'
Provides-Extra: pytables
Requires-Dist: tables (>=3.3.0); extra == 'pytables'
Provides-Extra: sas
Requires-Dist: sas7bdat (>=2.0.0); extra == 'sas'
Provides-Extra: sql
Requires-Dist: sqlalchemy (>=0.8.0); extra == 'sql'
Provides-Extra: ssh
Requires-Dist: paramiko (>=2.0.0); extra == 'ssh'
Provides-Extra: test
Requires-Dist: pytest (>=3.0.0); extra == 'test'
